soltrade.py
soltrade/__init__.py
soltrade/config.py
soltrade/indicators.py
soltrade/log.py
soltrade/trading.py
soltrade/transactions.py
soltrade/utils.py
soltrade/wallet.py
testing/backtest.py
soltrade-0.1.1.dist-info/LICENSE
soltrade-0.1.1.dist-info/METADATA
soltrade-0.1.1.dist-info/WHEEL
soltrade-0.1.1.dist-info/top_level.txt
soltrade-0.1.1.dist-info/RECORD
