Metadata-Version: 2.1
Name: soltrade
Version: 0.1.1
Summary: Soltrade is a Python-based, open source trading bot that we created in order to dive deeper into the workings of the blockchain and leap headfirst into the world of technical analysis
Author-email: noahtheprogrammer <noahtheprogrammer@gmail.com>
Project-URL: Homepage, https://github.com/noahtheprogrammer/soltrade
Classifier: Programming Language :: Python :: 3
Requires-Python: >=3.8
License-File: LICENSE
Requires-Dist: requests
Requires-Dist: typing-extensions
Requires-Dist: pycryptodome>=3.20.0
Requires-Dist: semantic-types>=0.1.4
Requires-Dist: pandas>=1.5.3
Requires-Dist: apscheduler>=3.10.1
Requires-Dist: matplotlib>=3.8
